{
  "cookies": [
    {
      "name": "session-username",
      "value": "standard_user",
      "domain": "www.saucedemo.com",
      "path": "/",
      "expires": 1717560115,
      "httpOnly": false,
      "secure": false,
      "sameSite": "Lax"
    }
  ],
  "origins": [
    {
      "origin": "https://www.saucedemo.com",
      "localStorage": [
        {
          "name": "backtrace-last-active",
          "value": "1717559514820"
        },
        {
          "name": "backtrace-guid",
          "value": "b7ca7540-b0de-41f0-a830-fe58ced7cb47"
        }
      ]
    }
  ]
}